OMOP_MEDS/__init__.py
OMOP_MEDS/__main__.py
OMOP_MEDS/commands.py
OMOP_MEDS/dataset.yaml
OMOP_MEDS/download.py
OMOP_MEDS/pre_meds.py
OMOP_MEDS/pre_meds_utils.py
OMOP_MEDS/configs/ETL.yaml
OMOP_MEDS/configs/OMOP.yaml
OMOP_MEDS/configs/__init__.py
OMOP_MEDS/configs/event_configs.yaml
OMOP_MEDS/configs/main.yaml
OMOP_MEDS/configs/pre_MEDS.yaml
OMOP_MEDS/configs/pre_MEDS_minimal.yaml
OMOP_MEDS/configs/runner.yaml
omop_meds-0.1.0.dist-info/licenses/LICENSE
omop_meds-0.1.0.dist-info/METADATA
omop_meds-0.1.0.dist-info/WHEEL
omop_meds-0.1.0.dist-info/entry_points.txt
omop_meds-0.1.0.dist-info/top_level.txt
omop_meds-0.1.0.dist-info/RECORD
