Metadata-Version: 2.4
Name: OMOP-MEDS
Version: 0.1.0
Summary: An ETL to convert OMOP data to the MEDS format.
Author-email: Robin van de Water <robin.vandewater@hpi.de>, Matthew McDermott <mattmcdermott8@gmail.com>
Project-URL: Homepage, https://github.com/rvandewater/OMOP_MEDS
Project-URL: Issues, https://github.com/rvandewater/OMOP_MEDS/issues
Classifier: Programming Language :: Python :: 3
Classifier: License :: OSI Approved :: MIT License
Classifier: Operating System :: OS Independent
Requires-Python: >=3.11
License-File: LICENSE
Requires-Dist: meds-transforms~=0.2.4
Requires-Dist: requests
Requires-Dist: beautifulsoup4
Requires-Dist: hydra-core
Requires-Dist: loguru
Requires-Dist: polars
Requires-Dist: omop_schema
Requires-Dist: meds~=0.3.3
Provides-Extra: dev
Requires-Dist: pre-commit<4; extra == "dev"
Requires-Dist: mdformat-admon; extra == "dev"
Provides-Extra: tests
Requires-Dist: pytest; extra == "tests"
Requires-Dist: pytest-cov; extra == "tests"
Provides-Extra: local-parallelism
Requires-Dist: hydra-joblib-launcher; extra == "local-parallelism"
Provides-Extra: slurm-parallelism
Requires-Dist: hydra-submitit-launcher; extra == "slurm-parallelism"
Dynamic: license-file
